{"settingEntity":{"suggestedColumnValues":["31.500,00, 32.400,00, 26.100,00, 40.500,00, 19.800,00, 27.000,00, 20.700,00, 21.600,00, 41.400,00, 34.200,00, 21.600,00, 78.300,00, 32.400,00, 28.800,00, 18.900,00, 18.000,00, 28.800,00, 18.000,00, 7.200,00, 35.100,00, 24.300,00, 35.100,00, 34.200,00, 27.900,00, 30.600,00, 69.300,00, 35.100,00, 34.200,00, 34.200,00, 23.400,00","9,00, 5,00, 6,50, 8,75, 6,00, 7,50, 9,25, 6,00, 9,25, 6,75, 5,25, 9,25, 10,00, 8,75, 8,25, 6,25, 10,00, 6,25, 10,00, 9,50, 5,00, 7,50, 6,25, 8,00, 8,00, 6,50, 8,00, 10,00, 8,25, 8,00","6,00, 2,00, 10,00, 4,00, 3,00, 1,00, 1,00, 3,00, 5,00, 8,00, 3,00, 8,00, 2,00, 3,00, 1,00, 2,00, 3,00, 2,00, 1,00, 4,00, 2,00, 1,00, 1,00, 4,00, 3,00, 7,00, 4,00, 4,00, 1,00, 3,00","38.230,00, 20.180,00, 31.989,00, 35.258,00, 24.487,00, 28.300,00, 34.548,00, 24.557,00, 37.836,00, 31.340,00, 21.874,00, 40.405,00, 38.076,00, 34.265,00, 30.936,00, 24.665,00, 39.007,00, 24.578,00, 37.267,00, 37.878,00, 20.220,00, 28.400,00, 23.882,00, 32.427,00, 31.699,00, 29.670,00, 32.789,00, 39.792,00, 30.935,00, 31.701,00"],"seedType":"default","harVideoAugmentations":0,"handPoseClassifierAugmentations":[],"featureNames":["wake","estimatedSleep","coffee"],"targetColumn":"actualSleep","handActionClassifierAugmentations":[],"augmentations":[],"transferLearningEmbeddingType":"dynamic","suggestedColumns":["wake","estimatedSleep","coffee","actualSleep"],"suggestedColumnTypes":["Double","Double","Double","Double"],"generalRegressorType":{"auto":{}},"styleTransferAlgorithmType":"image","algorithmType":"maxEnt","taskType":"generalRegresor"},"evaluationState":"uninitialized","id":"A02A5BFC-04D0-42E2-91C6-E03459E44A9D","contentDataResult":{"createdDate":"2024-06-30T19:51:07Z"},"trainingEntity":{"finishTime":"2024-06-30T19:54:11Z","validationResults":{"generalRegressor":{"rootMeanSquaredError":176.87807805762287,"maximumError":694.8439790218545}},"featureExtractionCheckpointMayBeAvailable":false,"trainingResults":{"generalRegressor":{"maximumError":700.7884351177563,"rootMeanSquaredError":177.06208892898567}},"progress":[],"analysedDataType":"datasource","dataSourceID":"B7A05294-6713-4889-A9E0-03D14E23C414","trainingAccuracy":177.06208892898567,"snapshottableCheckpoints":{},"startTime":"2024-06-30T19:54:10Z","checkpointMetrics":{},"dataResult":{"dataSourceID":"B7A05294-6713-4889-A9E0-03D14E23C414","dataURL":"file:\/\/\/Users\/caio\/Downloads\/HackingWithSwift-main\/SwiftUI\/project4-files\/BetterRest.csv","columnValues":["31.500,00, 32.400,00, 26.100,00, 40.500,00, 19.800,00, 27.000,00, 20.700,00, 21.600,00, 41.400,00, 34.200,00, 21.600,00, 78.300,00, 32.400,00, 28.800,00, 18.900,00, 18.000,00, 28.800,00, 18.000,00, 7.200,00, 35.100,00, 24.300,00, 35.100,00, 34.200,00, 27.900,00, 30.600,00, 69.300,00, 35.100,00, 34.200,00, 34.200,00, 23.400,00","9,00, 5,00, 6,50, 8,75, 6,00, 7,50, 9,25, 6,00, 9,25, 6,75, 5,25, 9,25, 10,00, 8,75, 8,25, 6,25, 10,00, 6,25, 10,00, 9,50, 5,00, 7,50, 6,25, 8,00, 8,00, 6,50, 8,00, 10,00, 8,25, 8,00","6,00, 2,00, 10,00, 4,00, 3,00, 1,00, 1,00, 3,00, 5,00, 8,00, 3,00, 8,00, 2,00, 3,00, 1,00, 2,00, 3,00, 2,00, 1,00, 4,00, 2,00, 1,00, 1,00, 4,00, 3,00, 7,00, 4,00, 4,00, 1,00, 3,00","38.230,00, 20.180,00, 31.989,00, 35.258,00, 24.487,00, 28.300,00, 34.548,00, 24.557,00, 37.836,00, 31.340,00, 21.874,00, 40.405,00, 38.076,00, 34.265,00, 30.936,00, 24.665,00, 39.007,00, 24.578,00, 37.267,00, 37.878,00, 20.220,00, 28.400,00, 23.882,00, 32.427,00, 31.699,00, 29.670,00, 32.789,00, 39.792,00, 30.935,00, 31.701,00"],"createdDate":"2024-06-30T19:51:07Z","dataAnalysis":{"summary":{"sampleCount":10000,"canUseValidation":1},"classifierAnalysis":{},"issues":[{"description":"Data has 10000 rows","severity":"info"}],"regressorAnalysis":{"targetRange":[19216,45224]}},"columns":["wake","estimatedSleep","coffee","actualSleep"],"columnTypes":["Double","Double","Double","Double"],"itemsCount":10000,"targetRange":[19216,45224]},"validationAccuracy":176.87807805762287},"validationEntity":{"dataResult":{"createdDate":"2024-06-30T19:51:07Z"},"analysedDataType":"auto"},"evaluationEntity":{"id":"8fc63991-522b-423f-aadc-3c60027f39c9","analysedDataType":"none","dataResult":{}},"createdDate":"2024-06-30T19:50:02Z","snapshotRole":{"withoutSnapshots":0},"evaluationContainerEntity":{"evaluationEntities":[{"id":"2e153f48-06cf-496d-aa42-0218eda4295b","createdDate":"2024-06-30T19:54:21Z","analysedDataType":"none","dataResult":{"createdDate":"2024-06-30T19:58:28Z"}}],"testingEvaluationEntity":{"dataResult":{"createdDate":"2024-06-30T19:51:07Z"},"createdDate":"2024-06-30T19:50:02Z","analysedDataType":"none","id":"f359ccd5-e3c3-4628-bec0-437fdd081ddb"},"validationEvaluationEntity":{"id":"7476b4c9-9f70-4246-95ee-dfbd4a7586fa","createdDate":"2024-06-30T19:50:02Z","dataResult":{"createdDate":"2024-06-30T19:51:07Z"},"analysedDataType":"auto","evaluationResult":{"generalRegressor":{"maximumError":694.8439790218545,"rootMeanSquaredError":176.87807805762287}}},"id":"659aebb7-314d-45af-84fc-25ebb65c7c5c","createdDate":"2024-06-30T19:58:33Z","previewType":"tabularRegressor","modifiedDate":"2024-06-30T19:58:33Z","trainingEvaluationEntity":{"dataSourceID":"B7A05294-6713-4889-A9E0-03D14E23C414","dataResult":{"dataSourceID":"B7A05294-6713-4889-A9E0-03D14E23C414","targetRange":[19216,45224],"dataAnalysis":{"regressorAnalysis":{"targetRange":[19216,45224]},"classifierAnalysis":{},"summary":{"sampleCount":10000,"canUseValidation":1},"issues":[{"description":"Data has 10000 rows","severity":"info"}]},"dataURL":"file:\/\/\/Users\/caio\/Downloads\/HackingWithSwift-main\/SwiftUI\/project4-files\/BetterRest.csv","createdDate":"2024-06-30T19:51:07Z","itemsCount":10000},"createdDate":"2024-06-30T19:50:02Z","id":"3244675a-8ace-4746-95fc-88543a65540d","analysedDataType":"none","evaluationResult":{"generalRegressor":{"rootMeanSquaredError":177.06208892898567,"maximumError":700.7884351177563}}}},"preferredFilename":"Kaffee 1","title":"Koffee 1","modifiedDate":"2024-06-30T19:58:33Z","modelEntity":{"modifiedDate":"2024-06-30T19:50:02Z","experimentID":"A02A5BFC-04D0-42E2-91C6-E03459E44A9D","title":"","modelURL":"Models\/Kaffee%201.mlmodel\/","version":"1.0","id":"ADC789B7-D02D-4F9D-BA3D-FDB1C4CE100A","preferredFilename":"","createdDate":"2024-06-30T19:50:02Z"},"activityEntities":["trainingFinished",[{"id":"3D41C47D-808A-4A0B-9702-590A4D8E7859","event":"trainingFinished","subtitle":"Kaffee 1","createdDate":"2024-06-30T19:54:11Z","title":"Training Completed"}],"trainingDataAdded",[{"event":"trainingDataAdded","subtitle":"BetterRest.csv","createdDate":"2024-06-30T19:51:07Z","title":"Training Data Added","id":"36F977B2-A71E-4652-995D-B383C14DDBEC"}],"trainingStarted",[{"event":"trainingStarted","title":"Training Started","subtitle":"Kaffee 1","createdDate":"2024-06-30T19:54:10Z","id":"7AE37642-E62C-443D-987B-EF421D885A95"}],"experimentCreated",[{"title":"Model Source Created","event":"experimentCreated","subtitle":"Kaffee 1","id":"0B8EC83C-DF58-4BB9-AD80-CCC7C2C76EEE","createdDate":"2024-06-30T19:50:02Z"}]],"state":"trained","version":"1.0"}